hoc/__init__.py
hoc/cli.py
house_of_cards-1.0.1.dist-info/LICENSE
house_of_cards-1.0.1.dist-info/METADATA
house_of_cards-1.0.1.dist-info/WHEEL
house_of_cards-1.0.1.dist-info/entry_points.txt
house_of_cards-1.0.1.dist-info/RECORD
