Metadata-Version: 2.1
Name: house-of-cards
Version: 1.0.1
Summary: A robust CLI tool to create directory structures from tree-like input.
License: GPL-3.0
Author: Your Name
Author-email: your.email@example.com
Requires-Python: >=3.8,<3.13
Classifier: License :: OSI Approved :: GNU General Public License v3 (GPLv3)
Classifier: Programming Language :: Python :: 3
Classifier: Programming Language :: Python :: 3.8
Classifier: Programming Language :: Python :: 3.9
Classifier: Programming Language :: Python :: 3.10
Classifier: Programming Language :: Python :: 3.11
Classifier: Programming Language :: Python :: 3.12
Requires-Dist: click (>=8.1.7,<9.0.0)
Requires-Dist: pyperclip (>=1.9.0,<2.0.0)
